feature_explorer/__init__.py
feature_explorer/application.py
feature_explorer-0.0.1.dist-info/LICENSE
feature_explorer-0.0.1.dist-info/METADATA
feature_explorer-0.0.1.dist-info/WHEEL
feature_explorer-0.0.1.dist-info/top_level.txt
feature_explorer-0.0.1.dist-info/RECORD
