Metadata-Version: 2.1
Name: feature-explorer
Version: 0.0.1
Summary: Web application for creating commonly useful data visualizations
Home-page: https://github.com/garzillo/feature_explorer
Author: Alberto Garza
Author-email: albertogarza22@gmail.com
License: UNKNOWN
Platform: UNKNOWN
Classifier: Programming Language :: Python :: 3
Classifier: License :: OSI Approved :: MIT License
